eincheck/__init__.py
eincheck/cache.py
eincheck/checks/.ipynb_checkpoints/data-checkpoint.py
eincheck/checks/__init__.py
eincheck/checks/data.py
eincheck/checks/func.py
eincheck/checks/shapes.py
eincheck/contexts.py
eincheck/parser/__init__.py
eincheck/parser/dim_spec.py
eincheck/parser/expressions.py
eincheck/parser/grammar.py
eincheck/parser/parse_cache.py
eincheck/parser/shape_spec.py
eincheck/py.typed
eincheck/types.py
eincheck/utils.py
eincheck-0.6.0.dist-info/LICENSE
eincheck-0.6.0.dist-info/METADATA
eincheck-0.6.0.dist-info/WHEEL
eincheck-0.6.0.dist-info/RECORD
