Metadata-Version: 2.1
Name: eincheck
Version: 0.6.0
Summary: Tensor shape checks inspired by einstein notation
Home-page: https://github.com/EPronovost/eincheck
License: MIT
Author: Ethan Pronovost
Author-email: epronovo1@gmail.com
Requires-Python: >=3.8.1,<4
Classifier: License :: OSI Approved :: MIT License
Classifier: Programming Language :: Python
Classifier: Programming Language :: Python :: 3
Classifier: Programming Language :: Python :: 3.9
Classifier: Programming Language :: Python :: 3.10
Classifier: Programming Language :: Python :: 3.11
Classifier: Programming Language :: Python :: 3.12
Classifier: Programming Language :: Python :: 3.13
Classifier: Programming Language :: Python :: 3.8
Requires-Dist: lark (>=1.1,<1.2)
Requires-Dist: typing-extensions (>=4.0,<5.0)
Project-URL: Documentation, https://eincheck.readthedocs.io/en/main/
Project-URL: Repository, https://github.com/EPronovost/eincheck
